IOGraph/__init__.py
IOGraph/__main__.py
IOGraph/conf.yml.dist
IOGraph-0.0.29.data/scripts/IOGraph
IOGraph-0.0.29.dist-info/LICENSE
IOGraph-0.0.29.dist-info/METADATA
IOGraph-0.0.29.dist-info/WHEEL
IOGraph-0.0.29.dist-info/top_level.txt
IOGraph-0.0.29.dist-info/RECORD
