Metadata-Version: 2.1
Name: IOGraph
Version: 0.0.29
Summary: Generate Plotly Graphs from IOZone Data
Home-page: http://pypi.python.org/Makr91/IOGraph/
Author: Mark Gilbert
Author-email: support@philotic.cloud
License: UNKNOWN
Platform: UNKNOWN
Classifier: Programming Language :: Python :: 3
Classifier: License :: OSI Approved :: Apache Software License
Classifier: Operating System :: OS Independent
Requires-Python: >=3.5
Requires-Dist: setuptools
Requires-Dist: pandas (>=0.22.0)
Requires-Dist: plotly (>=5.0.0rc2)
Requires-Dist: xlrd (>=2.0.1)
Requires-Dist: PyYAML (>=5.3.1)
Requires-Dist: dash (>=1.2.0)
Requires-Dist: Cython (>=0.29.23)
Requires-Dist: dash-core-components (>=1.16.0)
Requires-Dist: dash-html-components (>=1.1.3)
Requires-Dist: dash-renderer (>=1.9.1)
Requires-Dist: dash-table (>=4.11.3)
Requires-Dist: openpyxl (>=3.0.7)
Requires-Dist: argparse (>=1.4.0)
Requires-Dist: appdirs (>=1.4.4)
Requires-Dist: distro (>=1.5.0)
Requires-Dist: xlutils (>=2.0.0)
Requires-Dist: xlwt (>=1.3.0)
Requires-Dist: numpy (>=1.16.0)
